poetry_version_override_plugin/__init__.py
poetry_version_override_plugin/plugin.py
poetry_version_override_plugin-0.1.4.dist-info/LICENSE
poetry_version_override_plugin-0.1.4.dist-info/METADATA
poetry_version_override_plugin-0.1.4.dist-info/WHEEL
poetry_version_override_plugin-0.1.4.dist-info/entry_points.txt
poetry_version_override_plugin-0.1.4.dist-info/RECORD
