Metadata-Version: 2.1
Name: poetry-version-override-plugin
Version: 0.1.4
Summary: A Poetry plugin to override a version in a pyproject.toml from environment variable or build and publish command option
Home-page: https://github.com/godfryd/poetry-version-override-plugin
License: APACHE 2.0
Keywords: poetry,poetry-plugin,plugin,version,version-override
Author: Michal Nowikowski
Author-email: godfryd@gmail.com
Requires-Python: >=3.8,<4
Classifier: License :: Other/Proprietary License
Classifier: Programming Language :: Python :: 3
Classifier: Programming Language :: Python :: 3.8
Classifier: Programming Language :: Python :: 3.9
Classifier: Programming Language :: Python :: 3.10
Classifier: Programming Language :: Python :: 3.11
Classifier: Programming Language :: Python :: 3.12
Classifier: Topic :: Software Development
Classifier: Topic :: System :: Systems Administration
Classifier: Topic :: Utilities
Requires-Dist: poetry (>=1.2.0a1)
Requires-Dist: toml (>=0.10.2,<0.11.0)
Project-URL: Repository, https://github.com/godfryd/poetry-version-override-plugin
